senerpy/__init__.py
senerpy/betterpandas.py
senerpy/info.py
senerpy/solar_common.py
senerpy/solar_general.py
senerpy-0.0.8.dist-info/LICENSE.md
senerpy-0.0.8.dist-info/METADATA
senerpy-0.0.8.dist-info/WHEEL
senerpy-0.0.8.dist-info/top_level.txt
senerpy-0.0.8.dist-info/RECORD
