Metadata-Version: 2.1
Name: senerpy
Version: 0.0.8
Summary: Librerias para uso de Data Science por parte de SENER
Home-page: https://bitbucket.org/stulbfl/senerpy
Author: Julio Rodriguez
Author-email: julio.rodriguez@sener.es
License: UNKNOWN
Platform: UNKNOWN
Classifier: Programming Language :: Python :: 3
Classifier: License :: OSI Approved :: MIT License
Classifier: Operating System :: OS Independent
Requires-Python: >=3.8
License-File: LICENSE.md
